mlx_raclate/__init__.py
mlx_raclate/py.typed
mlx_raclate/models/__init__.py
mlx_raclate/models/base.py
mlx_raclate/models/gemma3_text.py
mlx_raclate/models/lfm2.py
mlx_raclate/models/modernbert.py
mlx_raclate/models/qwen3.py
mlx_raclate/models/t5gemma_encoder.py
mlx_raclate/tuner/TUNER.md
mlx_raclate/tuner/__init__.py
mlx_raclate/tuner/collators.py
mlx_raclate/tuner/datasets.py
mlx_raclate/tuner/model_card_utils.py
mlx_raclate/tuner/trainer.py
mlx_raclate/tuner/utils.py
mlx_raclate/utils/__init__.py
mlx_raclate/utils/server.py
mlx_raclate/utils/tokenizer_utils.py
mlx_raclate/utils/train.py
mlx_raclate/utils/utils.py
mlx_raclate-0.1.0b1.dist-info/METADATA
mlx_raclate-0.1.0b1.dist-info/WHEEL
mlx_raclate-0.1.0b1.dist-info/licenses/LICENSE
mlx_raclate-0.1.0b1.dist-info/RECORD
