Metadata-Version: 2.4
Name: mlx-raclate
Version: 0.1.0b1
Summary: Raclate is a python library to run and train models for Retrieval and Classification, built on top of MLX.
Author-email: pappitti <pap@pitti.io>
License-File: LICENSE
Requires-Python: >=3.13
Requires-Dist: datasets>=4.4.1
Requires-Dist: fastapi>=0.121.3
Requires-Dist: huggingface-hub>=0.36.0
Requires-Dist: jinja2>=3.1.6
Requires-Dist: mlx>=0.29.0
Requires-Dist: transformers>=4.57.1
Requires-Dist: uvicorn>=0.38.0
